code_analysis/__init__.py
code_analysis/analyzer.py
code_analysis/cli.py
code_analysis/code_mapper.py
code_analysis/issue_detector.py
code_analysis/reporter.py
code_analysis_tool-1.0.2.dist-info/licenses/LICENSE
code_analysis_tool-1.0.2.dist-info/METADATA
code_analysis_tool-1.0.2.dist-info/WHEEL
code_analysis_tool-1.0.2.dist-info/entry_points.txt
code_analysis_tool-1.0.2.dist-info/top_level.txt
code_analysis_tool-1.0.2.dist-info/RECORD
